pyngoST/pyngoST.py
pyngoST/pyngoST_utils.py
pyngoST-1.1.0.dist-info/LICENSE
pyngoST-1.1.0.dist-info/METADATA
pyngoST-1.1.0.dist-info/WHEEL
pyngoST-1.1.0.dist-info/top_level.txt
pyngoST-1.1.0.dist-info/RECORD
