Metadata-Version: 2.1
Name: pyngoST
Version: 1.1.0
Summary: pyngoST: fast, simultaneous and accurate and multiple sequence typing of Neisseria gonorrhoeae genome collections
Home-page: https://github.com/leosanbu/pyngoST
Author: Leonor Sanchez-Buso
Author-email: leonor.sanchez@fisabio.es
License: UNKNOWN
Platform: UNKNOWN
Requires-Dist: urllib3 (==1.26.6)
Requires-Dist: requests
Requires-Dist: biopython
Requires-Dist: pandas
Requires-Dist: pyfaidx
Requires-Dist: openpyxl
Requires-Dist: pyahocorasick
